LICENSE
README.md
setup.cfg
setup.py
py_contactually/__init__.py
py_contactually/py_contactually.py
py_contactually.egg-info/PKG-INFO
py_contactually.egg-info/SOURCES.txt
py_contactually.egg-info/dependency_links.txt
py_contactually.egg-info/requires.txt
py_contactually.egg-info/top_level.txt