Metadata-Version: 2.1
Name: py-contactually
Version: 1.0.4
Summary: A Python wrapper for the Contactually API V2
Home-page: https://github.com/thecircleisround/
Author: thecircleisround
License: MIT
Download-URL: https://github.com/thecircleisround/Python-Contactually-Wrapper/archive/refs/tags/V1.0.4.tar.gz
Keywords: Contactually,Contactually API,Contactually Wrapper,Wrapper
Platform: UNKNOWN
License-File: LICENSE
